scandir_rs-2.9.5.dist-info/METADATA
scandir_rs-2.9.5.dist-info/WHEEL
scandir_rs-2.9.5.dist-info/licenses/LICENSE
scandir_rs/__init__.py
scandir_rs/scandir_rs.cpython-313-x86_64-linux-gnu.so
scandir_rs-2.9.5.dist-info/RECORD
