Metadata-Version: 2.4
Name: scandir-rs
Version: 2.9.5
Classifier: Development Status :: 4 - Beta
Classifier: Intended Audience :: Developers
Classifier: Programming Language :: Rust
Classifier: Programming Language :: Python
Classifier: Programming Language :: Python :: 3
Classifier: Programming Language :: Python :: 3.10
Classifier: Programming Language :: Python :: 3.11
Classifier: Programming Language :: Python :: 3.12
Classifier: Programming Language :: Python :: 3.13
Classifier: Programming Language :: Python :: 3.14
Classifier: Programming Language :: Python
Classifier: Operating System :: POSIX :: Linux
Classifier: Operating System :: MacOS
Classifier: Operating System :: Microsoft :: Windows
Classifier: License :: OSI Approved :: MIT License
Classifier: Topic :: Software Development :: Libraries
Classifier: Topic :: Software Development :: Libraries :: Python Modules
Classifier: Topic :: Utilities
License-File: LICENSE
Summary: A fast file tree scanner written in Rust
Keywords: fast,scandir,walk
Home-Page: https://github.com/brmmm3/scandir-rs
Author: Martin Bammer <mrbm74@gmail.com>
Author-email: Martin Bammer <mrbm74@gmail.com>
License: MIT
Requires-Python: >=3.10
Project-URL: Source Code, https://github.com/brmmm3/scandir-rs
